opencensus/__init__.py
opencensus/ext/__init__.py
opencensus/ext/azure/__init__.py
opencensus/ext/azure/common/__init__.py
opencensus/ext/azure/common/exporter.py
opencensus/ext/azure/common/processor.py
opencensus/ext/azure/common/protocol.py
opencensus/ext/azure/common/storage.py
opencensus/ext/azure/common/transport.py
opencensus/ext/azure/common/utils.py
opencensus/ext/azure/common/version.py
opencensus/ext/azure/log_exporter/__init__.py
opencensus/ext/azure/metrics_exporter/__init__.py
opencensus/ext/azure/metrics_exporter/standard_metrics/__init__.py
opencensus/ext/azure/metrics_exporter/standard_metrics/cpu.py
opencensus/ext/azure/metrics_exporter/standard_metrics/http_requests.py
opencensus/ext/azure/metrics_exporter/standard_metrics/memory.py
opencensus/ext/azure/metrics_exporter/standard_metrics/process.py
opencensus/ext/azure/statsbeat/__init__.py
opencensus/ext/azure/statsbeat/state.py
opencensus/ext/azure/statsbeat/statsbeat.py
opencensus/ext/azure/statsbeat/statsbeat_metrics.py
opencensus/ext/azure/trace_exporter/__init__.py
opencensus_ext_azure-1.1.13.dist-info/METADATA
opencensus_ext_azure-1.1.13.dist-info/WHEEL
opencensus_ext_azure-1.1.13.dist-info/namespace_packages.txt
opencensus_ext_azure-1.1.13.dist-info/top_level.txt
opencensus_ext_azure-1.1.13.dist-info/RECORD
